uoy_assessment_uploader/__init__.py
uoy_assessment_uploader/__main__.py
uoy_assessment_uploader/argparse.py
uoy_assessment_uploader/constants.py
uoy_assessment_uploader/credentials.py
uoy_assessment_uploader/requests.py
uoy_assessment_uploader-1.2.1.dist-info/LICENSE
uoy_assessment_uploader-1.2.1.dist-info/METADATA
uoy_assessment_uploader-1.2.1.dist-info/WHEEL
uoy_assessment_uploader-1.2.1.dist-info/entry_points.txt
uoy_assessment_uploader-1.2.1.dist-info/top_level.txt
uoy_assessment_uploader-1.2.1.dist-info/RECORD
