Metadata-Version: 2.1
Name: uoy-assessment-uploader
Version: 1.2.1
Summary: Tool for automating submitting assessments to the University of York Computer Science department.
Author-email: jmcb <joelsgp@protonmail.com>
License: GNU GENERAL PUBLIC LICENSE
Project-URL: Home, https://github.com/joelsgp/uoy-assessment-uploader
Classifier: Development Status :: 4 - Beta
Classifier: Environment :: Console
Classifier: License :: OSI Approved :: GNU General Public License v3 or later (GPLv3+)
Classifier: Natural Language :: English
Classifier: Operating System :: OS Independent
Classifier: Topic :: Education
Classifier: Topic :: Utilities
Requires-Python: >=3.8
License-File: LICENSE
Requires-Dist: beautifulsoup4 ~=4.10.0
Requires-Dist: keyring ~=24.0.0
Requires-Dist: requests ~=2.28.0
